alfanous/__init__.py
alfanous/console.py
alfanous/constants.py
alfanous/data.py
alfanous/engines.py
alfanous/exceptions.py
alfanous/indexing.py
alfanous/misc.py
alfanous/outputs.py
alfanous/paths.py
alfanous/query_processing.py
alfanous/results_processing.py
alfanous/romanization.py
alfanous/searching.py
alfanous/suggestions.py
alfanous/text_processing.py
alfanous/Support/__init__.py
alfanous/Support/PyArabic/__init__.py
alfanous/Support/PyArabic/araby.py
alfanous/Support/PyArabic/araby_constants.py
alfanous/Support/PyArabic/araby_normalizers.py
alfanous/Support/PyArabic/araby_predicates.py
alfanous/Support/PyArabic/araby_statistics.py
alfanous/Support/PyArabic/araby_strip_functions.py
alfanous/Support/whoosh/__init__.py
alfanous/Support/whoosh/analysis.py
alfanous/Support/whoosh/classify.py
alfanous/Support/whoosh/fields.py
alfanous/Support/whoosh/formats.py
alfanous/Support/whoosh/highlight.py
alfanous/Support/whoosh/index.py
alfanous/Support/whoosh/postings.py
alfanous/Support/whoosh/query.py
alfanous/Support/whoosh/reading.py
alfanous/Support/whoosh/scoring.py
alfanous/Support/whoosh/searching.py
alfanous/Support/whoosh/spelling.py
alfanous/Support/whoosh/store.py
alfanous/Support/whoosh/system.py
alfanous/Support/whoosh/util.py
alfanous/Support/whoosh/writing.py
alfanous/Support/whoosh/filedb/__init__.py
alfanous/Support/whoosh/filedb/fileindex.py
alfanous/Support/whoosh/filedb/filepostings.py
alfanous/Support/whoosh/filedb/filereading.py
alfanous/Support/whoosh/filedb/filestore.py
alfanous/Support/whoosh/filedb/filetables.py
alfanous/Support/whoosh/filedb/filewriting.py
alfanous/Support/whoosh/filedb/postpool.py
alfanous/Support/whoosh/filedb/structfile.py
alfanous/Support/whoosh/lang/__init__.py
alfanous/Support/whoosh/lang/lovins.py
alfanous/Support/whoosh/lang/morph_en.py
alfanous/Support/whoosh/lang/paicehusk.py
alfanous/Support/whoosh/lang/porter.py
alfanous/Support/whoosh/lang/porter2.py
alfanous/Support/whoosh/lang/wordnet.py
alfanous-0.7.34.dist-info/METADATA
alfanous-0.7.34.dist-info/WHEEL
alfanous-0.7.34.dist-info/entry_points.txt
alfanous-0.7.34.dist-info/top_level.txt
alfanous-0.7.34.dist-info/RECORD
