Metadata-Version: 2.1
Name: alfanous
Version: 0.7.34
Summary: Quranic search engine API
Home-page: https://github.com/Alfanous-team/alfanous
Author: Assem Chelli
Author-email: assem.ch@gmail.com
License: AGPL
Keywords: quran search indexing engine alfanous
Platform: ALL
Classifier: Development Status :: 4 - Beta
Classifier: Intended Audience :: Developers
Classifier: License :: OSI Approved :: GNU Affero General Public License v3 or later (AGPLv3+)
Classifier: Natural Language :: Arabic
Classifier: Operating System :: OS Independent
Classifier: Programming Language :: Python :: 2.7
Classifier: Topic :: Software Development :: Libraries :: Python Modules
Requires-Dist: pyparsing
